btf_extractor/__init__.py
btf_extractor/c_ext/__init__.py
btf_extractor/c_ext/btf.hh
btf_extractor/c_ext/btf.pxd
btf_extractor/ubo2003.py
btf_extractor/ubo2014.pyx
ubo2014_cy.cpython-39-darwin.so
btf_extractor/ubo2014.cpp
btf_extractor-1.6.0.dist-info/LICENSE
btf_extractor-1.6.0.dist-info/WHEEL
btf_extractor-1.6.0.dist-info/METADATA
btf_extractor-1.6.0.dist-info/RECORD
