Metadata-Version: 2.1
Name: btf-extractor
Version: 1.6.0
Summary: Extract UBO BTF archive format(UBO2003, ATRIUM, UBO2014).
Home-page: https://github.com/2-propanol/btf_extractor
License: Zlib
Author: 2-propanol
Author-email: nuclear.fusion.247@gmail.com
Requires-Python: >=3.6,<4.0
Classifier: License :: OSI Approved
Classifier: Programming Language :: Python :: 3
Classifier: Programming Language :: Python :: 3.6
Classifier: Programming Language :: Python :: 3.7
Classifier: Programming Language :: Python :: 3.8
Classifier: Programming Language :: Python :: 3.9
Requires-Dist: Cython (>=0.29,<0.30)
Requires-Dist: imageio (>=2.6,<3.0)
Requires-Dist: nptyping (>=1,<2)
Requires-Dist: numpy (>=1.19,<2.0)
Requires-Dist: simplejpeg (>=1.3)
